langvae/__init__.py
langvae/arch/__init__.py
langvae/arch/vae.py
langvae/data_conversion/__init__.py
langvae/data_conversion/tokenization.py
langvae/decoders/__init__.py
langvae/decoders/sentence.py
langvae/encoders/__init__.py
langvae/encoders/automodel_presets.py
langvae/encoders/sentence.py
langvae/pipelines/__init__.py
langvae/pipelines/lang_training.py
langvae/trainers/__init__.py
langvae/trainers/cyclical_schedule_kl.py
langvae/trainers/training_callbacks.py
langvae-0.6.13.dist-info/LICENSE
langvae-0.6.13.dist-info/METADATA
langvae-0.6.13.dist-info/WHEEL
langvae-0.6.13.dist-info/top_level.txt
langvae-0.6.13.dist-info/RECORD
