Metadata-Version: 2.2
Name: langvae
Version: 0.6.13
Summary: LangVAE: Large Language VAEs made simple
Home-page: 
Author: Danilo S. Carvalho
Author-email: "Danilo S. Carvalho" <danilo.carvalho@manchester.ac.uk>
Project-URL: Homepage, https://github.com/neuro-symbolic-ai/LangVAE
Project-URL: Issues, https://github.com/neuro-symbolic-ai/LangVAE/issues
Keywords: vae,llm,generative,nlp
Classifier: Programming Language :: Python :: 3
Classifier: License :: OSI Approved :: GNU General Public License v3 (GPLv3)
Classifier: Operating System :: OS Independent
Requires-Python: >=3.11
License-File: LICENSE
Requires-Dist: pythae==0.1.2
Requires-Dist: torch>=2.4
Requires-Dist: transformers==4.48.0
Requires-Dist: jsonlines==4.0.0
Requires-Dist: xxhash==3.5.0
Requires-Dist: saf-nlp>=0.5.5
Requires-Dist: accelerate>=0.26.0
Dynamic: author
Dynamic: requires-python
